{
  "playerMoney": 1007822365,
  "charsToLevel": {
    "6": 1,
    "15.17": 1,
    "13.15.17": 2,
    "2.7.8.9.13.14.15.16.17": 1,
    "2.7.8.9.13.14.15.16": 3
  },
  "playerKillEnemy": [
    null,
    null,
    [
      191,
      113,
      126,
      7,
      7,
      7,
      6,
      0,
      0,
      0,
      0,
      0,
      0,
      5,
      9,
      9,
      10
    ],
    [
      16,
      0,
      0,
      36,
      47,
      0,
      0,
      0,
      0,
      0,
      0,
      0,
      0,
      1,
      1,
      1,
      0
    ],
    null,
    null,
    [
      17,
      79,
      4,
      2,
      1,
      0,
      0,
      0,
      0,
      0,
      0,
      0,
      0,
      8,
      0
    ],
    null,
    null,
    null,
    null,
    null,
    null,
    null,
    null,
    [
      16,
      1,
      0,
      0,
      0,
      0,
      0,
      0,
      0,
      0,
      0,
      0,
      0,
      0,
      0,
      0,
      0
    ],
    null,
    [
      78,
      50,
      59,
      1,
      0,
      0,
      0,
      0,
      0,
      0,
      0,
      0,
      0,
      0,
      0,
      0,
      0
    ],
    null,
    null,
    null,
    null,
    null,
    null,
    null,
    null,
    null
  ],
  "playerBeEnemyHurt": null,
  "playerExps": [
    0,
    0,
    2518,
    758,
    0,
    0,
    512,
    1259,
    1259,
    1259,
    0,
    0,
    0,
    1634,
    1259,
    1764,
    1259,
    1170,
    0,
    0,
    0,
    0,
    0,
    0,
    0,
    0,
    0
  ],
  "lastCharsIndexes": [
    15,
    -1,
    13,
    9,
    2,
    14,
    8,
    7,
    16,
    -1
  ],
  "language": 0,
  "playerExtras": [
    null,
    null,
    [
      0,
      0,
      0
    ],
    [
      0,
      0,
      0
    ],
    null,
    null,
    [
      0,
      0,
      0,
      0
    ],
    [
      0,
      0,
      0
    ],
    [
      0,
      0,
      0
    ],
    [
      0,
      0,
      0,
      0
    ],
    null,
    null,
    null,
    [
      1,
      0,
      1
    ],
    [
      0,
      0,
      0
    ],
    [
      0,
      1,
      0
    ],
    [
      0,
      0,
      0
    ],
    [
      1,
      2,
      1
    ],
    null,
    null,
    null,
    null,
    null,
    null,
    null,
    null,
    null
  ],
  "playerExtraData": [
    [
      0,
      0,
      0,
      0,
      0,
      0,
      0,
      0
    ],
    [
      0,
      0,
      0,
      0,
      0,
      0,
      0,
      0
    ],
    [
      0,
      1190,
      2075,
      0,
      4,
      3,
      15,
      15
    ],
    [
      3518,
      192,
      0,
      102,
      1,
      0,
      24,
      24
    ],
    [
      0,
      0,
      0,
      0,
      0,
      0,
      0,
      0
    ],
    [
      0,
      0,
      0,
      0,
      0,
      0,
      0,
      0
    ],
    [
      1337,
      212,
      0,
      111,
      2,
      1,
      22,
      22
    ],
    [
      617,
      1168,
      0,
      34,
      4,
      3,
      15,
      15
    ],
    [
      166,
      1168,
      0,
      0,
      4,
      3,
      15,
      15
    ],
    [
      0,
      1168,
      760,
      0,
      4,
      3,
      15,
      15
    ],
    [
      0,
      0,
      0,
      0,
      0,
      0,
      0,
      0
    ],
    [
      0,
      0,
      0,
      0,
      0,
      0,
      0,
      0
    ],
    [
      0,
      0,
      0,
      0,
      0,
      0,
      0,
      0
    ],
    [
      0,
      600,
      1462,
      0,
      4,
      3,
      19,
      19
    ],
    [
      0,
      3644,
      0,
      0,
      4,
      3,
      15,
      15
    ],
    [
      332,
      4739,
      1474,
      31,
      4,
      3,
      27,
      27
    ],
    [
      3999,
      584,
      0,
      342,
      4,
      3,
      15,
      15
    ],
    [
      3471,
      1129,
      9570,
      288,
      3,
      2,
      14,
      14
    ],
    [
      0,
      0,
      0,
      0,
      0,
      0,
      0,
      0
    ],
    [
      0,
      0,
      0,
      0,
      0,
      0,
      0,
      0
    ],
    [
      0,
      0,
      0,
      0,
      0,
      0,
      0,
      0
    ],
    [
      0,
      0,
      0,
      0,
      0,
      0,
      0,
      0
    ],
    [
      0,
      0,
      0,
      0,
      0,
      0,
      0,
      0
    ],
    [
      0,
      0,
      0,
      0,
      0,
      0,
      0,
      0
    ],
    [
      0,
      0,
      0,
      0,
      0,
      0,
      0,
      0
    ],
    [
      0,
      0,
      0,
      0,
      0,
      0,
      0,
      0
    ],
    [
      0,
      0,
      0,
      0,
      0,
      0,
      0,
      0
    ]
  ],
  "playerAddCharacteristics": [
    null,
    null,
    [
      0,
      0,
      0,
      0,
      0
    ],
    [
      0,
      0,
      0,
      0,
      0
    ],
    null,
    null,
    [
      0,
      0,
      3,
      0,
      0
    ],
    [
      0,
      0,
      0,
      0,
      0
    ],
    [
      0,
      0,
      0,
      0,
      0
    ],
    [
      0,
      0,
      0,
      0,
      0
    ],
    null,
    null,
    null,
    [
      0,
      0,
      0,
      0,
      0
    ],
    [
      0,
      0,
      0,
      0,
      0
    ],
    [
      0,
      0,
      0,
      0,
      0
    ],
    [
      0,
      0,
      0,
      0,
      0
    ],
    [
      0,
      0,
      0,
      3,
      0
    ],
    null,
    null,
    null,
    null,
    null,
    null,
    null,
    null,
    null
  ],
  "volumes": [
    0.0,
    1.0,
    1.0
  ],
  "maxCompanionNum": 10,
  "targetFrameRate": -1,
  "runInBackground": false,
  "windowed": true
}